axiros_utils-3.1.0.dist-info/WHEEL
axiros_utils-3.1.0.dist-info/entry_points.txt
axiros_utils-3.1.0.dist-info/top_level.txt
axiros_utils-3.1.0.dist-info/METADATA
axiros_utils-3.1.0.dist-info/RECORD
axiros_utils-3.1.0.dist-info/licenses/LICENSE
ax_utils/__init__.py
ax_utils/unicode_utils/monkey_patches.py
ax_utils/unicode_utils/_isutf8.c
ax_utils/unicode_utils/compat.h
ax_utils/unicode_utils/_isutf8.cpython-311-aarch64-linux-gnu.so
ax_utils/unicode_utils/_convert_nested.cpython-311-aarch64-linux-gnu.so
ax_utils/unicode_utils/_convert_nested.c
ax_utils/unicode_utils/__init__.py
ax_utils/simple_deepcopy/compat.h
ax_utils/simple_deepcopy/_simple_deepcopy.c
ax_utils/simple_deepcopy/_simple_deepcopy.cpython-311-aarch64-linux-gnu.so
ax_utils/simple_deepcopy/__init__.py
ax_utils/props_to_tree/compat.h
ax_utils/props_to_tree/_props_to_tree.cpython-311-aarch64-linux-gnu.so
ax_utils/props_to_tree/fallback.py
ax_utils/props_to_tree/__init__.py
ax_utils/props_to_tree/_props_to_tree.c
ax_utils/ax_queue/_ax_queue.cpython-311-aarch64-linux-gnu.so
ax_utils/ax_queue/compat.h
ax_utils/ax_queue/_ax_queue.cpp
ax_utils/ax_queue/__init__.py
ax_utils/ax_queue/gevent_patch.py
ax_utils/ax_tree/ax_tree.py
ax_utils/ax_tree/compat.h
ax_utils/ax_tree/_ax_tree.cpython-311-aarch64-linux-gnu.so
ax_utils/ax_tree/_ax_tree.c
ax_utils/ax_tree/__init__.py
ax_utils/ax_tree/stack.c
