Metadata-Version: 2.4
Name: axiros_utils
Version: 3.1.0
Summary: Standalone ax_utils package with C/C++ extensions for high-performance utilities
Author-email: axiros <gklessinger@gmx.de>
License-Expression: BSD-3-Clause
Project-URL: Homepage, https://github.com/axgkl/ax_utils
Project-URL: Documentation, https://github.com/axgkl/ax_utils#readme
Project-URL: Repository, https://github.com/axgkl/ax_utils.git
Project-URL: Bug Tracker, https://github.com/axgkl/ax_utils/issues
Keywords: utilities,performance,tree,queue,unicode
Classifier: Development Status :: 5 - Production/Stable
Classifier: Intended Audience :: Developers
Classifier: Operating System :: OS Independent
Classifier: Programming Language :: Python :: 3
Classifier: Programming Language :: Python :: 3.9
Classifier: Programming Language :: Python :: 3.10
Classifier: Programming Language :: Python :: 3.11
Classifier: Programming Language :: Python :: 3.12
Classifier: Programming Language :: C
Classifier: Programming Language :: C++
Classifier: Topic :: Software Development :: Libraries :: Python Modules
Requires-Python: >=3.9
License-File: LICENSE
Requires-Dist: setuptools
Dynamic: license-file
